gptme/__init__.py
gptme/assistant.py
gptme/conversation.py
gptme/models.py
gptme/adapters/__init__.py
gptme/adapters/_discord.py
gptme/images/image.py
gptme/images/image_to_text.py
gptme/images/ocr.py
gptme/utils/dataclass.py
gptme/utils/ocr.py
gptme/utils/semantic_search.py
gptme/utils/summarize.py
gptme/utils/templates.py
gptme/utils/timer.py
gptme/utils/web_search.py
gpt_me-0.1.0.dist-info/LICENSE
gpt_me-0.1.0.dist-info/WHEEL
gpt_me-0.1.0.dist-info/METADATA
gpt_me-0.1.0.dist-info/RECORD
