Metadata-Version: 2.1
Name: gpt-me
Version: 0.1.0
Summary: An experiment to replicate a fully self-sufficient, human-like chatbot that imitates you using various artificial intelligence models.
Keywords: gpt,ai,chatgpt,emulation
Author-email: TKDKid1000 <mail@tkdkid1000.net>
Requires-Python: >=3.7
Classifier: Development Status :: 3 - Alpha
Classifier: Programming Language :: Python :: 3
Classifier: License :: OSI Approved :: MIT License
Classifier: Natural Language :: English
Classifier: Operating System :: Unix
Requires-Dist: beautifulsoup4
Requires-Dist: black
Requires-Dist: gptrim
Requires-Dist: openai
Requires-Dist: Pillow
Requires-Dist: pytesseract
Requires-Dist: python-dotenv
Requires-Dist: requests
Requires-Dist: sentence-transformers
Requires-Dist: tenacity
Requires-Dist: tiktoken
Requires-Dist: torch
Requires-Dist: tqdm
Requires-Dist: transformers
Requires-Dist: discord.py-self ; extra == "adapters"
Requires-Dist: bumpver ; extra == "dev"
Requires-Dist: streamlit ; extra == "scripts"
Project-URL: Home, https://github.com/TKDKid1000/gpt-me
Provides-Extra: adapters
Provides-Extra: dev
Provides-Extra: scripts
